xdb_message_client.py
nadc_mqtt_helper/__init__.py
nadc_mqtt_helper/models.py
nadc_mqtt_helper/xdb_message_hub.py
nadc_mqtt_helper-0.1.11.dist-info/METADATA
nadc_mqtt_helper-0.1.11.dist-info/WHEEL
nadc_mqtt_helper-0.1.11.dist-info/top_level.txt
nadc_mqtt_helper-0.1.11.dist-info/RECORD
