Metadata-Version: 2.4
Name: nadc-mqtt-helper
Version: 0.1.11
Summary: NADC MQTT Helper Library
Author-email: xuyunfei <xuyf@nao.cas.cn>
Classifier: Programming Language :: Python :: 3
Classifier: License :: OSI Approved :: MIT License
Classifier: Operating System :: OS Independent
Requires-Python: >=3.6
Requires-Dist: paho-mqtt>=1.6.1
Requires-Dist: dataclasses>=0.6; python_version < "3.7"
Requires-Dist: python-dateutil>=2.8.0
